saldowsd-0.2.3.data/scripts/saldowsd
saldowsd-0.2.3.dist-info/METADATA
saldowsd-0.2.3.dist-info/WHEEL
saldowsd-0.2.3.dist-info/licenses/LICENSE
saldowsd/__init__.py
saldowsd/__main__.py
saldowsd/_find_saldowsd.py
saldowsd-0.2.3.dist-info/RECORD
