Metadata-Version: 2.4
Name: saldowsd
Version: 0.2.3
Classifier: Development Status :: 5 - Production/Stable
Classifier: Environment :: Console
Classifier: Intended Audience :: Developers
Classifier: Operating System :: OS Independent
Classifier: License :: OSI Approved :: MIT License
Classifier: License :: OSI Approved :: Apache Software License
Classifier: Programming Language :: Python
Classifier: Programming Language :: Python :: 3.8
Classifier: Programming Language :: Python :: 3.9
Classifier: Programming Language :: Python :: 3.10
Classifier: Programming Language :: Python :: 3.11
Classifier: Programming Language :: Python :: 3.12
Classifier: Programming Language :: Python :: 3.13
Classifier: Programming Language :: Python :: 3.14
Classifier: Programming Language :: Python :: 3 :: Only
Classifier: Topic :: Software Development :: Libraries
License-File: LICENSE
Summary: Tool for word sense disambiguation (WSD) based on SALDO, ported to Rust.
Keywords: word sense disambiguation,saldo
Author-email: Språkbanken Text <sb-info@svenska.gu.se>
Requires-Python: >=3.8
Project-URL: Homepage, https://spraakbanken.gu.se
Project-URL: Repository, https://github.com/spraakbanken/saldowsd-rs
Project-URL: Changelog, https://github.com/spraakbanken/saldowsd-rs/blob/main/CHANGELOG.md
Project-URL: Releases, https://github.com/spraakbanken/saldowsd-rs/releases
